autoTigerGraph/__init__.py
autoTigerGraph/autoTigerGraph.py
autoTigerGraph-0.0.3.dist-info/LICENSE
autoTigerGraph-0.0.3.dist-info/METADATA
autoTigerGraph-0.0.3.dist-info/WHEEL
autoTigerGraph-0.0.3.dist-info/top_level.txt
autoTigerGraph-0.0.3.dist-info/RECORD
