Metadata-Version: 2.1
Name: autoTigerGraph
Version: 0.0.3
Summary: A package for automaticaly generating TigerGraph schema and upserting data
Home-page: https://github.com/yaniv256/autoTigerGraph
Author: Yaniv Ben-Ami
Author-email: yaniv256@gmail.com
License: UNKNOWN
Platform: UNKNOWN
Classifier: Programming Language :: Python :: 3
Classifier: License :: OSI Approved :: MIT License
Classifier: Operating System :: Unix
Requires-Python: >=3.6
